interpolars/__init__.py
interpolars/_core.abi3.so
interpolars/_core.pyi
interpolars-0.1.0.dist-info/METADATA
interpolars-0.1.0.dist-info/WHEEL
interpolars-0.1.0.dist-info/licenses/LICENSE
interpolars-0.1.0.dist-info/RECORD
