Metadata-Version: 2.4
Name: interpolars
Version: 0.1.0
Requires-Dist: polars==1.37.1
License-File: LICENSE
Summary: Interpolation plugin for Polars
Keywords: polars,interpolation,plugin
Author-email: Benjamin Sobel <ben-developer@opayq.com>
Requires-Python: >=3.12
